alloy_python/__init__.py
alloy_python/constants.py
alloy_python/embedded/__init__.py
alloy_python/embedded/analytics.py
alloy_python/embedded/app.py
alloy_python/embedded/compliance.py
alloy_python/embedded/credentials.py
alloy_python/embedded/embedded.py
alloy_python/embedded/events.py
alloy_python/embedded/integrations.py
alloy_python/embedded/link.py
alloy_python/embedded/logs.py
alloy_python/embedded/tokens.py
alloy_python/embedded/users.py
alloy_python/embedded/workflows.py
alloy_python/uapi/__init__.py
alloy_python/uapi/accounting.py
alloy_python/uapi/commerce.py
alloy_python/uapi/crm.py
alloy_python/uapi/metadata.py
alloy_python/uapi/passthrough.py
alloy_python/uapi/uapi.py
alloy_python/uapi/user.py
alloy_python/uapi/webhooks.py
alloy_python-1.0.0.dist-info/METADATA
alloy_python-1.0.0.dist-info/WHEEL
alloy_python-1.0.0.dist-info/top_level.txt
alloy_python-1.0.0.dist-info/RECORD
