Metadata-Version: 2.1
Name: alloy-python
Version: 1.0.0
Summary: A lightweight Python wrapper for the Alloy API
Home-page: https://github.com/alloy-automation/alloy-python
Author: Alloy Automation Inc
Author-email: contact@runalloy.com
License: UNKNOWN
Platform: UNKNOWN
Classifier: Programming Language :: Python :: 3
Classifier: License :: OSI Approved :: MIT License
Classifier: Operating System :: OS Independent
Requires-Python: >=3.6
Requires-Dist: requests
